{
    "number": 793,
    "name": "Nihilego (Reduced Stats)",
    "base_hp": 5,
    "strength": "2/4",
    "dexterity": "2/4",
    "vitality": "1/3",
    "special": "2/5",
    "insight": "3/6",
    "moves": {
      "bronze": ["Wrap", "Pound", "Acid", "Tickle", "Constrict"],
      "silver": ["Acid Spray", "Clear Smog", "Power Split", "Guard Split", "Venoshock"],
      "gold": ["Headbutt", "Toxic Spikes", "Venom Drench", "Power Gem", "Stealth Rock", "Mirror Coat", "Wonder Room", "Head Smash"],
      "platinum": ["Foul Play", "Magic Coat", "Iron Head"],
      "diamond": []
    }
  }
  